hacs_fhir/__init__.py
hacs_fhir/py.typed
hacs_fhir-0.2.2.dist-info/METADATA
hacs_fhir-0.2.2.dist-info/WHEEL
hacs_fhir-0.2.2.dist-info/RECORD
