Metadata-Version: 2.4
Name: hacs-fhir
Version: 0.2.2
Summary: FHIR mapping functionality for HACS
Project-URL: Homepage, https://github.com/solanovisitor/hacs
Project-URL: Documentation, https://github.com/solanovisitor/hacs/blob/main/docs/README.md
Project-URL: Repository, https://github.com/solanovisitor/hacs
Project-URL: Bug Tracker, https://github.com/solanovisitor/hacs/issues
Project-URL: Changelog, https://github.com/solanovisitor/hacs/blob/main/docs/reference/changelog.md
Author-email: Solano Todeschini <solano.todeschini@gmail.com>
Maintainer-email: Solano Todeschini <solano.todeschini@gmail.com>
License: Apache-2.0
Keywords: agent,communication,fhir,healthcare,mapping
Classifier: Development Status :: 5 - Production/Stable
Classifier: Intended Audience :: Developers
Classifier: Intended Audience :: Healthcare Industry
Classifier: License :: OSI Approved :: Apache Software License
Classifier: Operating System :: OS Independent
Classifier: Programming Language :: Python
Classifier: Programming Language :: Python :: 3.10
Classifier: Programming Language :: Python :: 3.11
Classifier: Programming Language :: Python :: 3.12
Classifier: Programming Language :: Python :: 3.13
Classifier: Topic :: Scientific/Engineering :: Medical Science Apps.
Classifier: Topic :: Software Development :: Libraries :: Python Modules
Classifier: Typing :: Typed
Requires-Python: >=3.10
Requires-Dist: fhir-resources>=7.3.0
Requires-Dist: hacs-core
Requires-Dist: hacs-models
Requires-Dist: pydantic>=2.7.0
Provides-Extra: dev
Requires-Dist: pyright>=1.1.0; extra == 'dev'
Requires-Dist: pytest-cov>=4.0.0; extra == 'dev'
Requires-Dist: pytest>=7.0.0; extra == 'dev'
Requires-Dist: ruff>=0.4.0; extra == 'dev'
